Metadata-Version: 2.1
Name: dashes2
Version: 0.0.2
Summary: Dashes version 2
Home-page: UNKNOWN
Author: Arohan Arora
Author-email: novakcoolguy@gmail.com
License: UNKNOWN
Keywords: python,dashes2 package
Platform: UNKNOWN
Classifier: Development Status :: 3 - Alpha
Classifier: Intended Audience :: Education
Classifier: Programming Language :: Python :: 3
Classifier: Operating System :: MacOS :: MacOS X
Classifier: Operating System :: Microsoft :: Windows
Requires-Dist: streamlit
